{
  "businessCustomers": {},
  "admins": {
    "ADM001": {
      "username": "admin",
      "userID": "ADM001",
      "password": "3b612c75a7b5048a435fb6ec81e52ff92d6d795a8b5a9c17070f6a63c97a53b2",
      "name": "System",
      "surname": "0000000000",
      "branch": {
        "bankCode": "021",
        "branchCode": "0021"
      }
    }
  },
  "customers": {
    "CUS001": {
      "accounts": [],
      "username": "angelodiak",
      "userID": "CUS001",
      "password": "Diakoumis",
      "name": "Angelos",
      "surname": "Diakoumis",
      "branch": {
        "bankCode": "021",
        "branchCode": "0021"
      },
      "AFM": "123456789"
    },
    "CUS002": {
      "accounts": [],
      "username": "mike21",
      "userID": "CUS002",
      "password": "a043913351e3830bf1b0ecf679e0fa370c35aac7cc719e1036230a7c63b45807",
      "name": "Mike",
      "surname": "Oikonomou",
      "branch": {
        "bankCode": "021",
        "branchCode": "0021"
      },
      "AFM": "123456798"
    }
  },
  "bankEmployers": {},
  "auditors": {},
  "bankAccount": {
    "accountNumber": "BANK001",
    "balance": 1.0E8,
    "branch": {
      "bankCode": "021",
      "branchCode": "0021"
    }
  },
  "adminCount": 1,
  "customerCount": 2,
  "employeeCount": 0,
  "auditorCount": 0
}